menu_header_wagtail/__init__.py
menu_header_wagtail/models.py
menu_header_wagtail/wagtail_hooks.py
menu_header_wagtail/blocks/__init__.py
menu_header_wagtail/blocks/navbar_block.py
menu_header_wagtail/migrations/0001_initial.py
menu_header_wagtail/migrations/__init__.py
menu_header_wagtail/static/css/menu_header_wagtail.css
menu_header_wagtail/static/css/menu_header_wagtail.scss
menu_header_wagtail/static/css/wagtail_admin_header_ui.css
menu_header_wagtail/static/js/menu_header_wagtail.js
menu_header_wagtail/static/js/wagtail_admin_header_ui.js
menu_header_wagtail/templates/menu_header_wagtail/header_block.html
menu_header_wagtail/templates/menu_header_wagtail/menu/base_link_block.html
menu_header_wagtail/templates/menu_header_wagtail/menu/document_link_block.html
menu_header_wagtail/templates/menu_header_wagtail/menu/external_link_block.html
menu_header_wagtail/templates/menu_header_wagtail/menu/page_link_block.html
menu_header_wagtail/templatetags/__init__.py
menu_header_wagtail/templatetags/menu_header_wagtail_tag.py
menu_header_wagtail-1.0.1.dist-info/LICENSE.txt
menu_header_wagtail-1.0.1.dist-info/METADATA
menu_header_wagtail-1.0.1.dist-info/WHEEL
menu_header_wagtail-1.0.1.dist-info/top_level.txt
menu_header_wagtail-1.0.1.dist-info/RECORD
