Metadata-Version: 2.1
Name: menu-header-wagtail
Version: 1.0.1
Summary: Full navigation header, menus, sub menus, internal and external links and documents, simple integrated design.
Home-page: https://gitlab.com/florezjose/menu_header_wagtail
Author: Jose Flórez (@rojosefo)
Author-email: florezjoserdolfo@gmail.com
License: MIT
Download-URL: https://gitlab.com/florezjose/menu_header_wagtail/archive/1.0.1.tar.gz
Keywords: django,wagtail,fields,dynamic,theme,color,checkbox,boolean,choices,chooser,admin,python
Platform: UNKNOWN
Classifier: Development Status :: 5 - Production/Stable
Classifier: Environment :: Web Environment
Classifier: Framework :: Django
Classifier: Framework :: Django :: 3.0
Classifier: Framework :: Django :: 3.1
Classifier: Framework :: Wagtail
Classifier: Intended Audience :: Developers
Classifier: License :: OSI Approved :: MIT License
Classifier: Natural Language :: English
Classifier: Operating System :: OS Independent
Classifier: Programming Language :: Python :: 3
Classifier: Programming Language :: Python :: 3.4
Classifier: Programming Language :: Python :: 3.5
Classifier: Programming Language :: Python :: 3.6
Classifier: Programming Language :: Python :: 3.7
Classifier: Programming Language :: Python :: 3.8
Classifier: Topic :: Software Development :: Build Tools
Requires: django(>=3.0)
Requires: wagtail(>=2.8)
Requires-Dist: Django (>=3.0)
Requires-Dist: Pillow (<8.0.0,>=4.0.0)
